kivy3/__init__.py
kivy3/light.py
kivy3/materials.py
kivy3/renderer.py
kivy3/cameras/__init__.py
kivy3/cameras/camera.py
kivy3/cameras/orthographic_camera.py
kivy3/cameras/perspective_camera.py
kivy3/core/__init__.py
kivy3/core/face3.py
kivy3/core/geometry.py
kivy3/core/object3d.py
kivy3/extras/__init__.py
kivy3/extras/geometries.py
kivy3/loaders/__init__.py
kivy3/loaders/loader.py
kivy3/loaders/objloader.py
kivy3/loaders/stlloader.py
kivy3/math/__init__.py
kivy3/math/vectors.py
kivy3/objects/__init__.py
kivy3/objects/mesh.py
kivy3/scenes/__init__.py
kivy3/scenes/scene.py
kivy3-0.0.1.dev0.data/data/share/kivy3-examples/blinnphong.glsl
kivy3-0.0.1.dev0.data/data/share/kivy3-examples/createscene.py
kivy3-0.0.1.dev0.data/data/share/kivy3-examples/example1.py
kivy3-0.0.1.dev0.data/data/share/kivy3-examples/example2.py
kivy3-0.0.1.dev0.data/data/share/kivy3-examples/example3.py
kivy3-0.0.1.dev0.data/data/share/kivy3-examples/extended.glsl
kivy3-0.0.1.dev0.data/data/share/kivy3-examples/monkey.obj
kivy3-0.0.1.dev0.data/data/share/kivy3-examples/monkey.py
kivy3-0.0.1.dev0.data/data/share/kivy3-examples/simple.glsl
kivy3-0.0.1.dev0.data/data/share/kivy3-examples/test.stl
kivy3-0.0.1.dev0.data/data/share/kivy3-examples/testnurbs-2.mtl
kivy3-0.0.1.dev0.data/data/share/kivy3-examples/testnurbs-2.obj
kivy3-0.0.1.dev0.data/data/share/kivy3-examples/testnurbs.mtl
kivy3-0.0.1.dev0.data/data/share/kivy3-examples/testnurbs.obj
kivy3-0.0.1.dev0.data/data/share/kivy3-examples/camera/main.py
kivy3-0.0.1.dev0.data/data/share/kivy3-examples/textures/main.py
kivy3-0.0.1.dev0.data/data/share/kivy3-examples/textures/orion.mtl
kivy3-0.0.1.dev0.data/data/share/kivy3-examples/textures/orion.obj
kivy3-0.0.1.dev0.data/data/share/kivy3-examples/textures/orion.png
kivy3-0.0.1.dev0.data/data/share/kivy3-examples/textures/simple.glsl
kivy3-0.0.1.dev0.data/data/share/kivy3-examples/trackball/Digital.tga
kivy3-0.0.1.dev0.data/data/share/kivy3-examples/trackball/MQ-27-2.obj
kivy3-0.0.1.dev0.dist-info/LICENSE
kivy3-0.0.1.dev0.dist-info/METADATA
kivy3-0.0.1.dev0.dist-info/WHEEL
kivy3-0.0.1.dev0.dist-info/top_level.txt
kivy3-0.0.1.dev0.dist-info/RECORD
