Metadata-Version: 1.1
Name: kivy3
Version: 0.0.1.dev0
Summary: Kivy extensions for 3D graphics
Home-page: UNKNOWN
Author: Niko Skrypnik
Author-email: nskrypnik@gmail.com
License: UNKNOWN
Platform: UNKNOWN
Requires: kivy
